Metadata-Version: 2.1
Name: tencentserverless
Version: 0.1.2
Summary: This is callFunction for SCF.
Home-page: https://github.com/alanoluo/tencent-serverless-python.git
Author: Tencent Cloud
Author-email: qcloud_middleware@qq.com
License: Apache License 2.0
Keywords: scf
Platform: UNKNOWN
